_ra_wrapper.cp313-win_amd64.pyd
pdretro/__init__.py
pdretro/emulator.py
pdretro-0.2.1.dist-info/licenses/LICENSE
pdretro-0.2.1.dist-info/METADATA
pdretro-0.2.1.dist-info/WHEEL
pdretro-0.2.1.dist-info/top_level.txt
pdretro-0.2.1.dist-info/RECORD
