Metadata-Version: 2.4
Name: pdretro
Version: 0.2.1
Summary: Python wrapper for libretro cores
Author-email: Colin Politi <urboycolinthepanda@gmail.com>
License-Expression: MIT
Project-URL: homepage, https://github.com/ColinThePanda/pdretro
Project-URL: Bug_Tracker, https://github.com/ColinThePanda/pdretro/issues
Classifier: Programming Language :: Python :: 3
Classifier: Operating System :: OS Independent
Requires-Python: >=3.8
License-File: LICENSE
Requires-Dist: numpy>=1.20.0
Provides-Extra: test
Requires-Dist: pytest>=7.0.0; extra == "test"
Requires-Dist: Pillow>=9.0.0; extra == "test"
Dynamic: license-file
